savesubmitexam/__init__.py
savesubmitexam/savesubmitexamdummy.py
savesubmitexamdummy_sebastian_stigler-1.0.1.dist-info/LICENSE.txt
savesubmitexamdummy_sebastian_stigler-1.0.1.dist-info/METADATA
savesubmitexamdummy_sebastian_stigler-1.0.1.dist-info/WHEEL
savesubmitexamdummy_sebastian_stigler-1.0.1.dist-info/top_level.txt
savesubmitexamdummy_sebastian_stigler-1.0.1.dist-info/RECORD
