Metadata-Version: 2.1
Name: savesubmitexamdummy-sebastian-stigler
Version: 1.0.1
Summary: Dummy for SaveSubmitExam to be used in nbgrader
Home-page: https://in-stigler.htw-aalen.de/gitea/tools/savesubmitexamdummy
Author: Sebastian Stigler
Author-email: sebastian.stigler@hs-aalen.de
License: MIT
Project-URL: Documentation, https://pyscaffold.org/
Platform: any
Classifier: Development Status :: 4 - Beta
Classifier: Programming Language :: Python
License-File: LICENSE.txt
Requires-Dist: importlib-metadata ; python_version < "3.8"
Provides-Extra: testing
Requires-Dist: setuptools ; extra == 'testing'
Requires-Dist: pytest ; extra == 'testing'
Requires-Dist: pytest-cov ; extra == 'testing'
